anony_face.py
app/__init__.py
app/helpers.py
app/home.py
any_face-2.4.2.dist-info/METADATA
any_face-2.4.2.dist-info/WHEEL
any_face-2.4.2.dist-info/entry_points.txt
any_face-2.4.2.dist-info/top_level.txt
any_face-2.4.2.dist-info/RECORD
